README.md
setup.cfg
setup.py
sat_image/__init__.py
sat_image/apply_fmask.py
sat_image/bounds.py
sat_image/fmask.py
sat_image/image.py
sat_image/mtl.py
satellite_image.egg-info/PKG-INFO
satellite_image.egg-info/SOURCES.txt
satellite_image.egg-info/dependency_links.txt
satellite_image.egg-info/top_level.txt