Metadata-Version: 1.1
Name: satellite-image
Version: 0.1.1
Summary: Simple API provides a class to process satellite images
Home-page: https://github.com/dgketchum
Author: David Ketchum
Author-email: dgketchum@gmail.com
License: Apache
Download-URL: https://github.com/dgketchum/satellite_image/archive/0.1.1.tar.gz
Keywords: landsat modis hydrology remote sensing energy balance
Platform: Posix; MacOS X; Windows
Classifier: Development Status :: 1 - Planning
Classifier: Intended Audience :: Science/Research
Classifier: Topic :: Scientific/Engineering :: GIS
Classifier: License :: OSI Approved :: Apache Software License
Classifier: Programming Language :: Python :: 2.7
Classifier: Programming Language :: Python :: 3.5
